solum/__init__.py
solum/config.py
solum/i18n.py
solum/rpc.py
solum/version.py
solum/api/__init__.py
solum/api/app.py
solum/api/auth.py
solum/api/config.py
solum/api/controllers/__init__.py
solum/api/controllers/common_types.py
solum/api/controllers/root.py
solum/api/controllers/camp/__init__.py
solum/api/controllers/camp/camp_v1_1_endpoint.py
solum/api/controllers/camp/platform_endpoints.py
solum/api/controllers/camp/root.py
solum/api/controllers/camp/datamodel/__init__.py
solum/api/controllers/camp/datamodel/platform_endpoint.py
solum/api/controllers/camp/datamodel/platform_endpoints.py
solum/api/controllers/camp/v1_1/__init__.py
solum/api/controllers/camp/v1_1/assemblies.py
solum/api/controllers/camp/v1_1/attribute_definitions.py
solum/api/controllers/camp/v1_1/extensions.py
solum/api/controllers/camp/v1_1/formats.py
solum/api/controllers/camp/v1_1/parameter_definitions.py
solum/api/controllers/camp/v1_1/plans.py
solum/api/controllers/camp/v1_1/platform.py
solum/api/controllers/camp/v1_1/root.py
solum/api/controllers/camp/v1_1/services.py
solum/api/controllers/camp/v1_1/type_definitions.py
solum/api/controllers/camp/v1_1/uris.py
solum/api/controllers/camp/v1_1/datamodel/__init__.py
solum/api/controllers/camp/v1_1/datamodel/assemblies.py
solum/api/controllers/camp/v1_1/datamodel/attribute_definitions.py
solum/api/controllers/camp/v1_1/datamodel/extensions.py
solum/api/controllers/camp/v1_1/datamodel/format.py
solum/api/controllers/camp/v1_1/datamodel/formats.py
solum/api/controllers/camp/v1_1/datamodel/parameter_definitions.py
solum/api/controllers/camp/v1_1/datamodel/plans.py
solum/api/controllers/camp/v1_1/datamodel/platform.py
solum/api/controllers/camp/v1_1/datamodel/services.py
solum/api/controllers/camp/v1_1/datamodel/type_definitions.py
solum/api/controllers/camp/v1_1/datamodel/types.py
solum/api/controllers/v1/__init__.py
solum/api/controllers/v1/app.py
solum/api/controllers/v1/assembly.py
solum/api/controllers/v1/component.py
solum-15.0.0.dist-info/AUTHORS
solum-15.0.0.dist-info/LICENSE
solum-15.0.0.dist-info/METADATA
solum-15.0.0.dist-info/WHEEL
solum-15.0.0.dist-info/entry_points.txt
solum-15.0.0.dist-info/pbr.json
solum-15.0.0.dist-info/top_level.txt
solum-15.0.0.dist-info/RECORD
