Metadata-Version: 2.1
Name: solum
Version: 15.0.0
Summary: Application Lifecycle Management for OpenStack
Home-page: https://docs.openstack.org/solum/latest/
Author: OpenStack
Author-email: openstack-discuss@lists.openstack.org
License: UNKNOWN
Platform: UNKNOWN
Classifier: Environment :: OpenStack
Classifier: Intended Audience :: Information Technology
Classifier: Intended Audience :: System Administrators
Classifier: License :: OSI Approved :: Apache Software License
Classifier: Operating System :: POSIX :: Linux
Classifier: Programming Language :: Python
Classifier: Programming Language :: Python :: Implementation :: CPython
Classifier: Programming Language :: Python :: 3 :: Only
Classifier: Programming Language :: Python :: 3
Classifier: Programming Language :: Python :: 3.6
Classifier: Programming Language :: Python :: 3.7
Classifier: Programming Language :: Python :: 3.8
Classifier: Programming Language :: Python :: 3.9
Requires-Python: >=3.6
Requires-Dist: Babel (>=2.5.3)
Requires-Dist: SQLAlchemy (>=1.2.5)
Requires-Dist: WSME (>=0.10.0)
Requires-Dist: alembic (>=0.9.8)
Requires-Dist: debtcollector (>=1.2.0)
Requires-Dist: docker (>=3.1.1)
Requires-Dist: eventlet (>=0.26.1)
Requires-Dist: httplib2 (>=0.10.3)
Requires-Dist: iso8601 (>=0.1.12)
Requires-Dist: keystonemiddleware (>=4.21.0)
Requires-Dist: kombu (>=4.3.0)
Requires-Dist: netaddr (>=0.7.20)
Requires-Dist: oslo.config (>=6.8.0)
Requires-Dist: oslo.context (>=2.22.0)
Requires-Dist: oslo.db (>=4.40.0)
Requires-Dist: oslo.log (>=3.37.0)
Requires-Dist: oslo.messaging (>=5.36.0)
Requires-Dist: oslo.middleware (>=3.35.0)
Requires-Dist: oslo.policy (>=3.6.0)
Requires-Dist: oslo.privsep (>=1.33.2)
Requires-Dist: oslo.rootwrap (>=5.13.0)
Requires-Dist: oslo.serialization (>=2.25.0)
Requires-Dist: oslo.service (>=1.31.0)
Requires-Dist: oslo.upgradecheck (>=1.3.0)
Requires-Dist: oslo.utils (>=4.5.0)
Requires-Dist: pbr (>=3.1.1)
Requires-Dist: pecan (>=1.3.2)
Requires-Dist: python-barbicanclient (>=4.6.0)
Requires-Dist: python-glanceclient (>=2.9.1)
Requires-Dist: python-heatclient (>=1.14.0)
Requires-Dist: python-keystoneclient (>=3.15.0)
Requires-Dist: python-mistralclient (>=3.3.0)
Requires-Dist: python-neutronclient (>=6.7.0)
Requires-Dist: python-swiftclient (>=3.5.0)
Requires-Dist: python-zaqarclient (>=1.9.0)
